odoo8_addon_account_due_list-8.0.1.0.0-py2.7-nspkg.pth
odoo_addons/account_due_list/init_hook.py
odoo_addons/account_due_list/__openerp__.py
odoo_addons/account_due_list/__init__.py
odoo_addons/account_due_list/README.rst
odoo_addons/account_due_list/migrations/8.0.1.0.0/pre-migration.py
odoo_addons/account_due_list/models/account_move_line.py
odoo_addons/account_due_list/models/__init__.py
odoo_addons/account_due_list/i18n/it.po
odoo_addons/account_due_list/i18n/es.po
odoo_addons/account_due_list/i18n/sl.po
odoo_addons/account_due_list/i18n/account_due_list.pot
odoo_addons/account_due_list/i18n/de.po
odoo_addons/account_due_list/i18n/fr.po
odoo_addons/account_due_list/i18n/pt_BR.po
odoo_addons/account_due_list/views/payment_view.xml
odoo_addons/account_due_list/static/description/icon.png
odoo8_addon_account_due_list-8.0.1.0.0.dist-info/top_level.txt
odoo8_addon_account_due_list-8.0.1.0.0.dist-info/WHEEL
odoo8_addon_account_due_list-8.0.1.0.0.dist-info/RECORD
odoo8_addon_account_due_list-8.0.1.0.0.dist-info/metadata.json
odoo8_addon_account_due_list-8.0.1.0.0.dist-info/DESCRIPTION.rst
odoo8_addon_account_due_list-8.0.1.0.0.dist-info/METADATA
odoo8_addon_account_due_list-8.0.1.0.0.dist-info/namespace_packages.txt
